command_injection.py
command_injection-0.0.1.dist-info/METADATA
command_injection-0.0.1.dist-info/WHEEL
command_injection-0.0.1.dist-info/top_level.txt
command_injection-0.0.1.dist-info/RECORD
